tqsdk2/__init__.py
tqsdk2/_df.py
tqsdk2/_reverse_proxy.py
tqsdk2/_utils.py
tqsdk2/ta.py
tqsdk2/tafunc.py
tqsdk2/tqdatetime.py
tqsdk2/tqsdk2.cpython-312-x86_64-linux-gnu.so
tqsdk2/web/d3.min.js
tqsdk2/web/favicon.ico
tqsdk2/web/index.html
tqsdk2/web/manifest.json
tqsdk2/web/robots.txt
tqsdk2/web/service-worker.js
tqsdk2/web/css/app.d72d8978.css
tqsdk2/web/css/chunk-vendors.c93e9127.css
tqsdk2/web/fonts/ionicons.143146fa.woff2
tqsdk2/web/fonts/ionicons.99ac3308.woff
tqsdk2/web/fonts/ionicons.d535a25a.ttf
tqsdk2/web/img/ionicons.a2c4a261.svg
tqsdk2/web/img/icons/android-chrome-192x192.png
tqsdk2/web/img/icons/android-icon-144x144.png
tqsdk2/web/img/icons/android-icon-192x192.png
tqsdk2/web/img/icons/android-icon-36x36.png
tqsdk2/web/img/icons/android-icon-48x48.png
tqsdk2/web/img/icons/android-icon-72x72.png
tqsdk2/web/img/icons/android-icon-96x96.png
tqsdk2/web/img/icons/apple-touch-icon-114x114.png
tqsdk2/web/img/icons/apple-touch-icon-120x120.png
tqsdk2/web/img/icons/apple-touch-icon-144x144.png
tqsdk2/web/img/icons/apple-touch-icon-152x152.png
tqsdk2/web/img/icons/apple-touch-icon-180x180.png
tqsdk2/web/img/icons/apple-touch-icon-57x57.png
tqsdk2/web/img/icons/apple-touch-icon-60x60.png
tqsdk2/web/img/icons/apple-touch-icon-72x72.png
tqsdk2/web/img/icons/apple-touch-icon-76x76.png
tqsdk2/web/img/icons/apple-touch-icon-precomposed.png
tqsdk2/web/img/icons/apple-touch-icon.png
tqsdk2/web/img/icons/browserconfig.xml
tqsdk2/web/img/icons/favicon-16x16.png
tqsdk2/web/img/icons/favicon-32x32.png
tqsdk2/web/img/icons/favicon-96x96.png
tqsdk2/web/img/icons/favicon.ico
tqsdk2/web/img/icons/manifest.json
tqsdk2/web/img/icons/ms-icon-150x150.png
tqsdk2/web/img/icons/ms-icon-310x310.png
tqsdk2/web/img/icons/ms-icon-70x70.png
tqsdk2/web/img/icons/msapplication-icon-144x144.png.png
tqsdk2/web/img/icons/mstile-150x150.png
tqsdk2/web/img/icons/notes
tqsdk2/web/js/app.fc01ac28.js
tqsdk2/web/js/chunk-vendors.d7fceff6.js
tqsdk2-2.3.3.dist-info/METADATA
tqsdk2-2.3.3.dist-info/WHEEL
tqsdk2-2.3.3.dist-info/top_level.txt
tqsdk2-2.3.3.dist-info/RECORD
