Metadata-Version: 2.1
Name: tqsdk2
Version: 2.3.3
Summary: TianQin SDK2
Author: TianQin
Author-email: tianqincn@gmail.com
Requires-Dist: tqsdk2-fclib (==2.3.3)
Requires-Dist: numpy
Requires-Dist: pandas
Requires-Dist: scipy
Requires-Dist: aiohttp
